shared_lib/__init__.py
shared_lib/admin.py
shared_lib/apps.py
shared_lib/forms.py
shared_lib/models.py
shared_lib/sitemaps.py
shared_lib/urls.py
shared_lib/utils.py
shared_lib/views.py
shared_lib/migrations/0001_initial.py
shared_lib/migrations/0002_alter_modallinkvideo_bg_alter_modalrotatebg_bg_and_more.py
shared_lib/migrations/0003_calendar_event.py
shared_lib/migrations/0004_blogcategory_portfoliocategory_portfolio_profile_and_more.py
shared_lib/migrations/0005_alter_blogpost_content.py
shared_lib/migrations/0006_eventtype_alter_portfolio_subtitle_and_more.py
shared_lib/migrations/__init__.py
shared_lib/static/shared_lib/fullcalendar4/packages/bootstrap/LICENSE.txt
shared_lib/static/shared_lib/fullcalendar4/packages/bootstrap/README.md
shared_lib/static/shared_lib/fullcalendar4/packages/bootstrap/main.css
shared_lib/static/shared_lib/fullcalendar4/packages/bootstrap/main.d.ts
shared_lib/static/shared_lib/fullcalendar4/packages/bootstrap/main.esm.js
shared_lib/static/shared_lib/fullcalendar4/packages/bootstrap/main.js
shared_lib/static/shared_lib/fullcalendar4/packages/bootstrap/main.min.css
shared_lib/static/shared_lib/fullcalendar4/packages/bootstrap/main.min.js
shared_lib/static/shared_lib/fullcalendar4/packages/bootstrap/package.json
shared_lib/static/shared_lib/fullcalendar4/packages/core/LICENSE.txt
shared_lib/static/shared_lib/fullcalendar4/packages/core/README.md
shared_lib/static/shared_lib/fullcalendar4/packages/core/locales-all.js
shared_lib/static/shared_lib/fullcalendar4/packages/core/locales-all.min.js
shared_lib/static/shared_lib/fullcalendar4/packages/core/main.css
shared_lib/static/shared_lib/fullcalendar4/packages/core/main.d.ts
shared_lib/static/shared_lib/fullcalendar4/packages/core/main.esm.js
shared_lib/static/shared_lib/fullcalendar4/packages/core/main.js
shared_lib/static/shared_lib/fullcalendar4/packages/core/main.min.css
shared_lib/static/shared_lib/fullcalendar4/packages/core/main.min.js
shared_lib_ds-1.5.4.dist-info/WHEEL
shared_lib_ds-1.5.4.dist-info/METADATA
shared_lib_ds-1.5.4.dist-info/RECORD
