Metadata-Version: 2.4
Name: shared_lib_ds
Version: 1.5.4
Summary: Demiansoft template(shared_lib)
Requires-Python: >=3.6
Requires-Dist: Django>=4.2.11
Requires-Dist: Pillow>=10.4.0
Requires-Dist: django-easymde>=1.0.4
Requires-Dist: django-hitcount>=1.3.5
Requires-Dist: django-taggit>=6.1.0
Requires-Dist: django-jazzmin>=3.0.1
Requires-Dist: django-markdownx>=4.0.7
Requires-Dist: utils_hj3415>=3.2.0
